israeliqueue.cpython-313-x86_64-linux-gnu.so
israeliqueue/__init__.pyi
israeliqueue/__init__.pyx
israeliqueue/py.typed
cisraeliqueue-0.0.1a2.dist-info/LICENSE
cisraeliqueue-0.0.1a2.dist-info/METADATA
cisraeliqueue-0.0.1a2.dist-info/RECORD
cisraeliqueue-0.0.1a2.dist-info/WHEEL
cisraeliqueue-0.0.1a2.dist-info/top_level.txt
