Metadata-Version: 2.1
Name: cisraeliqueue
Version: 0.0.1a2
Summary: A fast implementation of an Israeli Queue
Author-email: Bar Harel <bzvi7919@gmail.com>
Project-URL: Homepage, https://github.com/bharel/cisraeliqueue
Project-URL: Documentation, https://cisraeliqueue.readthedocs.io/en/latest/
Project-URL: Source, https://github.com/bharel/cisraeliqueue
Project-URL: Changelog, https://github.com/bharel/cisraeliqueue/blob/master/changelog.md
Keywords: israeli queue,queue,priority queue
Classifier: Development Status :: 3 - Alpha
Classifier: Intended Audience :: Developers
Classifier: License :: OSI Approved :: MIT License
Classifier: Operating System :: OS Independent
Classifier: Framework :: AsyncIO
Classifier: Programming Language :: Cython
Classifier: Programming Language :: Python :: 3
Classifier: Programming Language :: Python :: 3.12
Classifier: Programming Language :: Python :: 3.13
Classifier: Programming Language :: Python :: 3.14
Classifier: Topic :: Internet
Classifier: Topic :: Utilities
Classifier: Topic :: Software Development :: Libraries :: Python Modules
Classifier: Typing :: Typed
Requires-Python: >=3.12
License-File: LICENSE
Provides-Extra: dev
Requires-Dist: flake8 ; extra == 'dev'
Requires-Dist: isort ; extra == 'dev'
Requires-Dist: mypy ; extra == 'dev'
Requires-Dist: git-cliff ; extra == 'dev'
Requires-Dist: sphinx ; extra == 'dev'
Requires-Dist: python-docs-theme ; extra == 'dev'
Requires-Dist: coverage ; extra == 'dev'
Requires-Dist: ruff ; extra == 'dev'
